paddlehelix/__init__.py
paddlehelix/api_client.py
paddlehelix/configuration.py
paddlehelix/exceptions.py
paddlehelix/qps_exceptions.py
paddlehelix/qps_utils.py
paddlehelix/rest.py
paddlehelix/sdk_exceptions.py
paddlehelix/api/__init__.py
paddlehelix/api/bce_api.py
paddlehelix/api/code.py
paddlehelix/api/config.py
paddlehelix/api/helixfold3_api.py
paddlehelix/api/registry.py
paddlehelix/api/task.py
paddlehelix/api/task_api.py
paddlehelix/cli/__init__.py
paddlehelix/cli/client.py
paddlehelix/models/__init__.py
paddlehelix/models/helix_task_info.py
paddlehelix/models/helixfold3_entity.py
paddlehelix/models/helixfold3_price_query_request.py
paddlehelix/models/helixfold3_price_query_response.py
paddlehelix/models/helixfold3_task.py
paddlehelix/models/helixfold3_task_batch_submit_request.py
paddlehelix/models/helixfold3_task_batch_submit_response.py
paddlehelix/models/helixfold3_task_batch_submit_response_data.py
paddlehelix/models/helixfold3_task_submit_response.py
paddlehelix/models/helixfold3_task_submit_response_data.py
paddlehelix/models/quary_balance_response.py
paddlehelix/models/task_cancel_request.py
paddlehelix/models/task_cancel_response.py
paddlehelix/models/task_get_request.py
paddlehelix/models/task_get_response.py
paddlehelix/models/task_price_info.py
paddlehelix/models/task_price_infos.py
paddlehelix/models/tasks_cancel_request.py
paddlehelix/models/tasks_cancel_response.py
paddlehelix/models/tasks_get_request.py
paddlehelix/models/tasks_get_response.py
paddlehelix/task/__init__.py
paddlehelix/task/common.py
paddlehelix/task/helixfold3.py
paddlehelix/utils/__init__.py
paddlehelix/utils/file_util.py
paddlehelix/utils/graceful_shutdown.py
paddlehelix/utils/logger.py
paddlehelix/utils/paddlehelix_utils.py
paddlehelix/version/__init__.py
paddlehelix/version/structures.py
paddlehelix_sdk-2.1.1.dist-info/licenses/LICENSE
paddlehelix_sdk-2.1.1.dist-info/METADATA
paddlehelix_sdk-2.1.1.dist-info/WHEEL
paddlehelix_sdk-2.1.1.dist-info/top_level.txt
paddlehelix_sdk-2.1.1.dist-info/RECORD
