Metadata-Version: 2.4
Name: paddlehelix-sdk
Version: 2.1.1
Summary: PaddleHelix SDK
Author-email: Paddlehelix Team <bcp@baidu.com>
Project-URL: Homepage, https://gitee.com/paddlehelix/paddlehelix
Classifier: Programming Language :: Python :: 3
Classifier: Operating System :: OS Independent
Classifier: License :: OSI Approved :: Apache Software License
Requires-Python: >=3.7
License-File: LICENSE
Requires-Dist: requests~=2.32.3
Requires-Dist: pyyaml~=6.0.2
Requires-Dist: pandas
Requires-Dist: termcolor~=2.4.0
Requires-Dist: six
Requires-Dist: python-dateutil
Requires-Dist: urllib3~=1.26.20
Requires-Dist: certifi
Requires-Dist: tabulate
Dynamic: license-file
